{
  "resourceType": "Questionnaire",
  "id": "SCAPE-CH",
  "title": "SCAPE-CH",
  "name": "SCAPE-Fragebogen",
  "status": "active",
  "meta": {
    "security": [
      {
        "system": "http://midata.coop/codesystems/security",
        "code": "public"
      }
    ]
  },
  "code": [
    {
      "system": "http://www.krebsliga.ch",
      "code": "scape-ch",
      "display": "SCAPE-CH Questionnaire"
    }
  ],
  "url": "http://www.krebsliga.ch/prem/SCAPE-CH",
  "version": "2.0",
  "item": [
    {
      "linkId": "1",
      "prefix": "1",
      "text": "Wurden Ihnen die möglichen Nebenwirkungen der Behandlung(en) in verständlicher Weise erklärt?",
      "type": "choice",
      "required": false,
      "answerOption": [
        {
          "valueCoding": {
            "code": "chirurgie",
            "display": "Chirurgie"
          }
        },
        {
          "valueCoding": {
            "code": "Chemotherapie",
            "display": "Chemotherapie"
          }
        },
        {
          "valueCoding": {
            "code": "Strahlentherapie",
            "display": "Strahlentherapie"
          }
        },
        {
          "valueCoding": {
            "code": "Hormontherapie",
            "display": "Hormontherapie"
          }
        },
        {
          "valueCoding": {
            "code": "Immuntherapie",
            "display": "Immuntherapie"
          }
        },
        {
          "valueCoding": {
            "code": "ZielgerichteteTherapie",
            "display": "Zielgerichtete Therapie"
          }
        },
        {
          "valueCoding": {
            "code": "noTreatment",
            "display": "Ich habe noch keine Behandlung erhalten"
          }
        },
        {
          "valueCoding": {
            "code": "over12months",
            "display": "Ich habe meine Behandlung(en) vor mehr als 12 Monaten erhalten"
          }
        },
        {
          "valueCoding": {
            "code": "idk",
            "display": "Ich weisses nicht"
          }
        },
        {
          "valueCoding": {
            "code": "Andere",
            "display": "Andere"
          }
        }
      ],
      "item": [
        {
          "linkId": "1.1",
          "prefix": "1.1",
          "text": "",
          "type": "string",
          "enableWhen": [
            {
              "question": "1",
              "operator": "=",
              "answerCoding": {
                "code": "Andere",
                "display": "Andere"
              }
            }
          ],
          "required": false
        }
      ]
    }
  ]
}
