{
    "valueCoding": {
        "code": "1",
        "display": "",
        "_display": {
            "extension": [
                {
                    "url": "http://hl7.org/fhir/StructureDefinition/translation",
                    "extension": [
                      {
                        "url": "lang",
                        "valueCode": "de"
                      },
                      {
                        "url": "content",
                        "valueString": ""
                      }
                    ]
                  },
                {
                    "url": "http://hl7.org/fhir/StructureDefinition/translation",
                    "extension": [
                      {
                        "url": "lang",
                        "valueCode": "fr"
                      },
                      {
                        "url": "content",
                        "valueString": ""
                      }
                    ]
                  }
            ]
        }
    }
},